<?xml version="1.0" encoding="utf-8" ?>
<dwsync>
<file name="homepage.jpg" server="ftp.wknown.com" local="131566480800000000" remote="131566480800000000" Dst="1" />
<file name="analytics.jpg" server="ftp.wknown.com" local="131566480800000000" remote="131566480800000000" Dst="1" />
<file name="sem.jpg" server="ftp.wknown.com" local="131566480800000000" remote="131566480800000000" Dst="1" />
<file name="seo.jpg" server="ftp.wknown.com" local="131566480800000000" remote="131566480800000000" Dst="1" />
<file name="smm.jpg" server="ftp.wknown.com" local="131566480800000000" remote="131566480800000000" Dst="1" />
<file name="display.jpg" server="ftp.wknown.com" local="131566480800000000" remote="131566480800000000" Dst="1" />
<file name="about-us.jpg" server="ftp.wknown.com" local="131568040200000000" remote="131568040200000000" Dst="1" />
<file name="about-us.jpeg" server="ftp.wknown.com" local="131595747117483556" remote="131616478800000000" Dst="1" />
<file name="display.jpeg" server="ftp.wknown.com" local="131595747171408027" remote="131616478800000000" Dst="1" />
<file name="analytics.jpeg" server="ftp.wknown.com" local="131595747168642457" remote="131616478800000000" Dst="1" />
<file name="sem.jpeg" server="ftp.wknown.com" local="131595747169182826" remote="131616478800000000" Dst="1" />
<file name="smm.jpeg" server="ftp.wknown.com" local="131595747249165143" remote="131616478800000000" Dst="1" />
<file name="seo.jpeg" server="ftp.wknown.com" local="131595747226716090" remote="131616478800000000" Dst="1" />
<file name="webdesign.jpg" server="ftp.wknown.com" local="131632457980779753" remote="131626732800000000" Dst="1" />
</dwsync>